video_extract_frames_mcp/__init__.py
video_extract_frames_mcp/main.py
mcpcn_video_extract_frames_mcp-0.1.4.dist-info/METADATA
mcpcn_video_extract_frames_mcp-0.1.4.dist-info/WHEEL
mcpcn_video_extract_frames_mcp-0.1.4.dist-info/entry_points.txt
mcpcn_video_extract_frames_mcp-0.1.4.dist-info/RECORD
